spk_derivatives/__init__.py
spk_derivatives/binomial.py
spk_derivatives/context_translator.py
spk_derivatives/data_loader.py
spk_derivatives/data_loader_nasa.py
spk_derivatives/export_snapshot.py
spk_derivatives/live_data.py
spk_derivatives/monte_carlo.py
spk_derivatives/plots.py
spk_derivatives/report.py
spk_derivatives/results_manager.py
spk_derivatives/sensitivities.py
spk_derivatives/solar_convergence_demo.py
spk_derivatives-0.2.0.dist-info/licenses/LICENSE
spk_derivatives-0.2.0.dist-info/METADATA
spk_derivatives-0.2.0.dist-info/WHEEL
spk_derivatives-0.2.0.dist-info/entry_points.txt
spk_derivatives-0.2.0.dist-info/top_level.txt
spk_derivatives-0.2.0.dist-info/RECORD
