Metadata-Version: 2.4
Name: spk-derivatives
Version: 0.2.0
Summary: Quantitative pricing framework for solar energy derivatives using NASA satellite data
Home-page: https://github.com/Spectating101/spk-derivatives
Author: SPK Derivatives Team
Author-email: SPK Derivatives Team <s1133958@mail.yzu.edu.tw>
Maintainer-email: SPK Derivatives Team <s1133958@mail.yzu.edu.tw>
License: MIT
Project-URL: Homepage, https://github.com/Spectating101/spk-derivatives
Project-URL: Documentation, https://github.com/Spectating101/spk-derivatives/blob/main/README.md
Project-URL: Repository, https://github.com/Spectating101/spk-derivatives
Project-URL: Bug Reports, https://github.com/Spectating101/spk-derivatives/issues
Keywords: solar,energy,derivatives,pricing,quantitative-finance,renewable-energy,NASA,satellite-data
Classifier: Development Status :: 4 - Beta
Classifier: Intended Audience :: Science/Research
Classifier: Intended Audience :: Financial and Insurance Industry
Classifier: Topic :: Scientific/Engineering :: Mathematics
Classifier: Topic :: Office/Business :: Financial
Classifier: License :: OSI Approved :: MIT License
Classifier: Programming Language :: Python :: 3
Classifier: Programming Language :: Python :: 3.8
Classifier: Programming Language :: Python :: 3.9
Classifier: Programming Language :: Python :: 3.10
Classifier: Programming Language :: Python :: 3.11
Classifier: Programming Language :: Python :: 3.12
Requires-Python: >=3.8
License-File: LICENSE
Requires-Dist: numpy>=1.20.0
Requires-Dist: pandas>=1.3.0
Requires-Dist: requests>=2.26.0
Requires-Dist: scipy>=1.7.0
Provides-Extra: viz
Requires-Dist: matplotlib>=3.4.0; extra == "viz"
Requires-Dist: seaborn>=0.11.0; extra == "viz"
Provides-Extra: dev
Requires-Dist: pytest>=7.0.0; extra == "dev"
Requires-Dist: pytest-cov>=3.0.0; extra == "dev"
Requires-Dist: black>=22.0.0; extra == "dev"
Requires-Dist: flake8>=4.0.0; extra == "dev"
Requires-Dist: mypy>=0.950; extra == "dev"
Requires-Dist: ipython>=8.0.0; extra == "dev"
Requires-Dist: jupyter>=1.0.0; extra == "dev"
Provides-Extra: api
Requires-Dist: fastapi>=0.95.0; extra == "api"
Requires-Dist: uvicorn>=0.21.0; extra == "api"
Requires-Dist: pydantic>=1.10.0; extra == "api"
Provides-Extra: dashboard
Requires-Dist: streamlit>=1.20.0; extra == "dashboard"
Requires-Dist: plotly>=5.13.0; extra == "dashboard"
Provides-Extra: all
Requires-Dist: matplotlib>=3.4.0; extra == "all"
Requires-Dist: seaborn>=0.11.0; extra == "all"
Requires-Dist: pytest>=7.0.0; extra == "all"
Requires-Dist: pytest-cov>=3.0.0; extra == "all"
Requires-Dist: fastapi>=0.95.0; extra == "all"
Requires-Dist: uvicorn>=0.21.0; extra == "all"
Requires-Dist: streamlit>=1.20.0; extra == "all"
Requires-Dist: plotly>=5.13.0; extra == "all"
Dynamic: author
Dynamic: home-page
Dynamic: license-file
Dynamic: requires-python
